UNLICENSE
qqbot_linger/__init__.py
qqbot_linger/main.py
qqbot_linger-0.2.1.dist-info/METADATA
qqbot_linger-0.2.1.dist-info/WHEEL
qqbot_linger-0.2.1.dist-info/entry_points.txt
qqbot_linger-0.2.1.dist-info/RECORD
