Metadata-Version: 2.1
Name: qqbot-linger
Version: 0.2.1
Summary: My QQ Bot for personal use
Home-page: https://github.com/7sDream/qqbot-linger
License: Unlicense
Keywords: nonebot,bilibili,qqbot
Author: 7sDream
Author-email: i@7sdre.am
Requires-Python: >=3.9,<4.0
Classifier: Development Status :: 3 - Alpha
Classifier: License :: OSI Approved :: The Unlicense (Unlicense)
Classifier: License :: Other/Proprietary License
Classifier: Operating System :: OS Independent
Classifier: Programming Language :: Python :: 3
Classifier: Programming Language :: Python :: 3.9
Classifier: Programming Language :: Python :: 3.10
Classifier: Programming Language :: Python :: 3.11
Requires-Dist: nonebot-plugin-7s-roll (>=0.2.0,<0.3.0)
Requires-Dist: nonebot-plugin-bam (>=0.2.1,<0.3.0)
Requires-Dist: nonebot2[fastapi] (==2.0.0)
Requires-Dist: pydantic (==1.10.9)
Project-URL: Repository, https://github.com/7sDream/qqbot-linger
